LICENSE
MANIFEST.in
README.md
requirements.txt
setup.py
xplenty/__init__.py
xplenty/exceptions.py
xplenty/xplenty_api.py
xplenty.egg-info/PKG-INFO
xplenty.egg-info/SOURCES.txt
xplenty.egg-info/dependency_links.txt
xplenty.egg-info/requires.txt
xplenty.egg-info/top_level.txt