Metadata-Version: 1.1
Name: xplenty
Version: 1.2.0
Summary: Xplenty API Python SDK
Home-page: https://github.com/xplenty/xplenty.py
Author: Xplenty
Author-email: opensource@xplenty.com
License: MIT
Platform: UNKNOWN
Classifier: Programming Language :: Python :: 2.7
Classifier: Programming Language :: Python :: 3
